prefectplus/__init__.py
prefectplus/__main__.py
prefectplus/environments.py
prefectplus-1.1.8.dist-info/LICENSE.txt
prefectplus-1.1.8.dist-info/METADATA
prefectplus-1.1.8.dist-info/WHEEL
prefectplus-1.1.8.dist-info/top_level.txt
prefectplus-1.1.8.dist-info/RECORD
